wox_plugin/__init__.py
wox_plugin/types.py
wox_plugin-0.1.0.dist-info/METADATA
wox_plugin-0.1.0.dist-info/WHEEL
wox_plugin-0.1.0.dist-info/top_level.txt
wox_plugin-0.1.0.dist-info/RECORD
