Metadata-Version: 2.1
Name: wox-plugin
Version: 0.1.0
Summary: Python types for Wox plugins
Home-page: https://github.com/Wox-launcher/Wox
Author: Wox-launcher
Author-email: 
Requires-Python: >=3.8
Provides-Extra: dev
Requires-Dist: build>=1.2.2.post1; extra == "dev"
Requires-Dist: twine>=6.0.1; extra == "dev"
